PaiEngine/setup.py
paiengine-0.0.5.dist-info/METADATA
paiengine-0.0.5.dist-info/WHEEL
paiengine-0.0.5.dist-info/top_level.txt
paiengine-0.0.5.dist-info/RECORD
