Metadata-Version: 2.4
Name: PaiEngine
Version: 0.0.5
Summary: PaiEngine - UI engine
Home-page: https://github.com/Pai100707/PaiEngine
Author: Pai100707
Classifier: Programming Language :: Python :: 3
Classifier: License :: OSI Approved :: MIT License
Classifier: Operating System :: OS Independent
Requires-Dist: pygame>=2.0.0
Dynamic: author
Dynamic: classifier
Dynamic: description
Dynamic: description-content-type
Dynamic: home-page
Dynamic: requires-dist
Dynamic: summary
